[
  {
    "date": "2008-06-03T00:00:00.000Z",
    "value": 185.37
  },
  {
    "date": "2008-06-04T00:00:00.000Z",
    "value": 185.19
  },
  {
    "date": "2008-06-05T00:00:00.000Z",
    "value": 189.43
  },
  {
    "date": "2008-06-06T00:00:00.000Z",
    "value": 185.64
  },
  {
    "date": "2008-06-09T00:00:00.000Z",
    "value": 181.61
  },
  {
    "date": "2008-06-09T00:00:00.000Z",
    "value": 185.64
  },
  {
    "date": "2008-06-10T00:00:00.000Z",
    "value": 180.81
  },
  {
    "date": "2008-06-11T00:00:00.000Z",
    "value": 173.26
  },
  {
    "date": "2008-06-12T00:00:00.000Z",
    "value": 172.37
  },
  {
    "date": "2008-06-15T00:00:00.000Z",
    "value": 176.84
  },
  {
    "date": "2008-06-16T00:00:00.000Z",
    "value": 181.43
  },
  {
    "date": "2008-06-17T00:00:00.000Z",
    "value": 178.75
  },
  {
    "date": "2008-06-18T00:00:00.000Z",
    "value": 180.9
  },
  {
    "date": "2008-06-19T00:00:00.000Z",
    "value": 175.27
  },
  {
    "date": "2008-06-22T00:00:00.000Z",
    "value": 173.16
  },
  {
    "date": "2008-06-23T00:00:00.000Z",
    "value": 173.25
  },
  {
    "date": "2008-06-24T00:00:00.000Z",
    "value": 177.39
  },
  {
    "date": "2008-06-25T00:00:00.000Z",
    "value": 168.26
  },
  {
    "date": "2008-06-26T00:00:00.000Z",
    "value": 170.09
  },
  {
    "date": "2008-06-29T00:00:00.000Z",
    "value": 167.44
  },
  {
    "date": "2008-07-01T00:00:00.000Z",
    "value": 174.68
  },
  {
    "date": "2008-07-02T00:00:00.000Z",
    "value": 168.18
  },
  {
    "date": "2008-07-03T00:00:00.000Z",
    "value": 170.12
  },
  {
    "date": "2008-07-07T00:00:00.000Z",
    "value": 175.16
  },
  {
    "date": "2008-07-08T00:00:00.000Z",
    "value": 179.55
  },
  {
    "date": "2008-07-09T00:00:00.000Z",
    "value": 174.25
  },
  {
    "date": "2008-07-09T00:00:00.000Z",
    "value": 176.63
  },
  {
    "date": "2008-07-10T00:00:00.000Z",
    "value": 172.58
  },
  {
    "date": "2008-07-13T00:00:00.000Z",
    "value": 173.88
  },
  {
    "date": "2008-07-14T00:00:00.000Z",
    "value": 169.64
  },
  {
    "date": "2008-07-15T00:00:00.000Z",
    "value": 172.81
  },
  {
    "date": "2008-07-16T00:00:00.000Z",
    "value": 171.81
  },
  {
    "date": "2008-07-17T00:00:00.000Z",
    "value": 165.15
  },
  {
    "date": "2008-07-20T00:00:00.000Z",
    "value": 166.29
  },
  {
    "date": "2008-07-21T00:00:00.000Z",
    "value": 162.02
  },
  {
    "date": "2008-07-22T00:00:00.000Z",
    "value": 166.26
  },
  {
    "date": "2008-07-23T00:00:00.000Z",
    "value": 159.03
  },
  {
    "date": "2008-07-24T00:00:00.000Z",
    "value": 162.12
  },
  {
    "date": "2008-07-27T00:00:00.000Z",
    "value": 154.4
  },
  {
    "date": "2008-07-28T00:00:00.000Z",
    "value": 157.08
  },
  {
    "date": "2008-07-29T00:00:00.000Z",
    "value": 159.88
  },
  {
    "date": "2008-07-30T00:00:00.000Z",
    "value": 158.95
  },
  {
    "date": "2008-08-01T00:00:00.000Z",
    "value": 156.66
  },
  {
    "date": "2008-08-04T00:00:00.000Z",
    "value": 153.23
  },
  {
    "date": "2008-08-05T00:00:00.000Z",
    "value": 160.64
  },
  {
    "date": "2008-08-06T00:00:00.000Z",
    "value": 164.19
  },
  {
    "date": "2008-08-07T00:00:00.000Z",
    "value": 163.57
  },
  {
    "date": "2008-08-08T00:00:00.000Z",
    "value": 169.55
  },
  {
    "date": "2008-08-10T00:00:00.000Z",
    "value": 173.56
  },
  {
    "date": "2008-08-11T00:00:00.000Z",
    "value": 176.73
  },
  {
    "date": "2008-08-12T00:00:00.000Z",
    "value": 179.3
  },
  {
    "date": "2008-08-13T00:00:00.000Z",
    "value": 179.32
  },
  {
    "date": "2008-08-14T00:00:00.000Z",
    "value": 175.74
  },
  {
    "date": "2008-08-17T00:00:00.000Z",
    "value": 175.39
  },
  {
    "date": "2008-08-18T00:00:00.000Z",
    "value": 173.53
  },
  {
    "date": "2008-08-19T00:00:00.000Z",
    "value": 175.84
  },
  {
    "date": "2008-08-20T00:00:00.000Z",
    "value": 174.29
  },
  {
    "date": "2008-08-21T00:00:00.000Z",
    "value": 176.79
  },
  {
    "date": "2008-08-24T00:00:00.000Z",
    "value": 172.55
  },
  {
    "date": "2008-08-25T00:00:00.000Z",
    "value": 173.64
  },
  {
    "date": "2008-08-26T00:00:00.000Z",
    "value": 174.67
  },
  {
    "date": "2008-08-27T00:00:00.000Z",
    "value": 173.74
  },
  {
    "date": "2008-08-28T00:00:00.000Z",
    "value": 169.53
  },
  {
    "date": "2008-09-02T00:00:00.000Z",
    "value": 166.19
  },
  {
    "date": "2008-09-03T00:00:00.000Z",
    "value": 166.96
  },
  {
    "date": "2008-09-04T00:00:00.000Z",
    "value": 161.22
  },
  {
    "date": "2008-09-05T00:00:00.000Z",
    "value": 160.18
  },
  {
    "date": "2008-09-08T00:00:00.000Z",
    "value": 157.92
  },
  {
    "date": "2008-09-09T00:00:00.000Z",
    "value": 151.68
  },
  {
    "date": "2008-09-09T00:00:00.000Z",
    "value": 151.61
  },
  {
    "date": "2008-09-10T00:00:00.000Z",
    "value": 152.65
  },
  {
    "date": "2008-09-11T00:00:00.000Z",
    "value": 148.94
  },
  {
    "date": "2008-09-14T00:00:00.000Z",
    "value": 140.36
  },
  {
    "date": "2008-09-15T00:00:00.000Z",
    "value": 139.88
  },
  {
    "date": "2008-09-16T00:00:00.000Z",
    "value": 127.83
  },
  {
    "date": "2008-09-17T00:00:00.000Z",
    "value": 134.09
  },
  {
    "date": "2008-09-18T00:00:00.000Z",
    "value": 140.91
  },
  {
    "date": "2008-09-21T00:00:00.000Z",
    "value": 131.05
  },
  {
    "date": "2008-09-22T00:00:00.000Z",
    "value": 126.84
  },
  {
    "date": "2008-09-23T00:00:00.000Z",
    "value": 128.71
  },
  {
    "date": "2008-09-24T00:00:00.000Z",
    "value": 131.93
  },
  {
    "date": "2008-09-25T00:00:00.000Z",
    "value": 128.24
  },
  {
    "date": "2008-09-28T00:00:00.000Z",
    "value": 105.26
  },
  {
    "date": "2008-09-29T00:00:00.000Z",
    "value": 113.66
  },
  {
    "date": "2008-10-01T00:00:00.000Z",
    "value": 109.12
  },
  {
    "date": "2008-10-02T00:00:00.000Z",
    "value": 100.1
  },
  {
    "date": "2008-10-03T00:00:00.000Z",
    "value": 97.07
  },
  {
    "date": "2008-10-06T00:00:00.000Z",
    "value": 98.14
  },
  {
    "date": "2008-10-07T00:00:00.000Z",
    "value": 89.16
  },
  {
    "date": "2008-10-08T00:00:00.000Z",
    "value": 89.79
  },
  {
    "date": "2008-10-09T00:00:00.000Z",
    "value": 88.74
  },
  {
    "date": "2008-10-09T00:00:00.000Z",
    "value": 96.8
  },
  {
    "date": "2008-10-12T00:00:00.000Z",
    "value": 110.26
  },
  {
    "date": "2008-10-13T00:00:00.000Z",
    "value": 104.08
  },
  {
    "date": "2008-10-14T00:00:00.000Z",
    "value": 97.95
  },
  {
    "date": "2008-10-15T00:00:00.000Z",
    "value": 101.89
  },
  {
    "date": "2008-10-16T00:00:00.000Z",
    "value": 97.4
  },
  {
    "date": "2008-10-19T00:00:00.000Z",
    "value": 98.44
  },
  {
    "date": "2008-10-20T00:00:00.000Z",
    "value": 91.49
  },
  {
    "date": "2008-10-21T00:00:00.000Z",
    "value": 96.87
  },
  {
    "date": "2008-10-22T00:00:00.000Z",
    "value": 98.23
  },
  {
    "date": "2008-10-23T00:00:00.000Z",
    "value": 96.38
  },
  {
    "date": "2008-10-26T00:00:00.000Z",
    "value": 92.09
  },
  {
    "date": "2008-10-27T00:00:00.000Z",
    "value": 99.91
  },
  {
    "date": "2008-10-28T00:00:00.000Z",
    "value": 104.55
  },
  {
    "date": "2008-10-29T00:00:00.000Z",
    "value": 111.04
  },
  {
    "date": "2008-10-30T00:00:00.000Z",
    "value": 107.59
  },
  {
    "date": "2008-11-03T00:00:00.000Z",
    "value": 106.96
  },
  {
    "date": "2008-11-04T00:00:00.000Z",
    "value": 110.99
  },
  {
    "date": "2008-11-05T00:00:00.000Z",
    "value": 103.3
  },
  {
    "date": "2008-11-06T00:00:00.000Z",
    "value": 99.1
  },
  {
    "date": "2008-11-07T00:00:00.000Z",
    "value": 98.24
  },
  {
    "date": "2008-11-09T00:00:00.000Z",
    "value": 95.88
  },
  {
    "date": "2008-11-10T00:00:00.000Z",
    "value": 94.77
  },
  {
    "date": "2008-11-11T00:00:00.000Z",
    "value": 90.12
  },
  {
    "date": "2008-11-12T00:00:00.000Z",
    "value": 96.44
  },
  {
    "date": "2008-11-13T00:00:00.000Z",
    "value": 90.24
  },
  {
    "date": "2008-11-16T00:00:00.000Z",
    "value": 88.14
  },
  {
    "date": "2008-11-17T00:00:00.000Z",
    "value": 89.91
  },
  {
    "date": "2008-11-18T00:00:00.000Z",
    "value": 86.29
  },
  {
    "date": "2008-11-19T00:00:00.000Z",
    "value": 80.49
  },
  {
    "date": "2008-11-20T00:00:00.000Z",
    "value": 82.58
  },
  {
    "date": "2008-11-23T00:00:00.000Z",
    "value": 92.95
  },
  {
    "date": "2008-11-24T00:00:00.000Z",
    "value": 90.8
  },
  {
    "date": "2008-11-25T00:00:00.000Z",
    "value": 95
  },
  {
    "date": "2008-11-26T00:00:00.000Z",
    "value": 95
  },
  {
    "date": "2008-11-27T00:00:00.000Z",
    "value": 92.67
  },
  {
    "date": "2008-12-01T00:00:00.000Z",
    "value": 88.93
  },
  {
    "date": "2008-12-02T00:00:00.000Z",
    "value": 92.47
  },
  {
    "date": "2008-12-03T00:00:00.000Z",
    "value": 95.9
  },
  {
    "date": "2008-12-04T00:00:00.000Z",
    "value": 91.41
  },
  {
    "date": "2008-12-05T00:00:00.000Z",
    "value": 94
  },
  {
    "date": "2008-12-08T00:00:00.000Z",
    "value": 99.72
  },
  {
    "date": "2008-12-09T00:00:00.000Z",
    "value": 100.06
  },
  {
    "date": "2008-12-09T00:00:00.000Z",
    "value": 98.21
  },
  {
    "date": "2008-12-10T00:00:00.000Z",
    "value": 95
  },
  {
    "date": "2008-12-11T00:00:00.000Z",
    "value": 98.27
  },
  {
    "date": "2008-12-14T00:00:00.000Z",
    "value": 94.75
  },
  {
    "date": "2008-12-15T00:00:00.000Z",
    "value": 95.43
  },
  {
    "date": "2008-12-16T00:00:00.000Z",
    "value": 89.16
  },
  {
    "date": "2008-12-17T00:00:00.000Z",
    "value": 89.43
  },
  {
    "date": "2008-12-18T00:00:00.000Z",
    "value": 90
  },
  {
    "date": "2008-12-21T00:00:00.000Z",
    "value": 85.74
  },
  {
    "date": "2008-12-22T00:00:00.000Z",
    "value": 86.38
  },
  {
    "date": "2008-12-23T00:00:00.000Z",
    "value": 85.04
  },
  {
    "date": "2008-12-24T00:00:00.000Z",
    "value": 85.04
  },
  {
    "date": "2008-12-25T00:00:00.000Z",
    "value": 85.81
  },
  {
    "date": "2008-12-28T00:00:00.000Z",
    "value": 86.61
  },
  {
    "date": "2008-12-29T00:00:00.000Z",
    "value": 86.29
  },
  {
    "date": "2008-12-30T00:00:00.000Z",
    "value": 85.35
  },
  {
    "date": "2009-01-01T00:00:00.000Z",
    "value": 85.35
  },
  {
    "date": "2009-01-02T00:00:00.000Z",
    "value": 90.75
  },
  {
    "date": "2009-01-05T00:00:00.000Z",
    "value": 94.58
  },
  {
    "date": "2009-01-06T00:00:00.000Z",
    "value": 93.02
  },
  {
    "date": "2009-01-07T00:00:00.000Z",
    "value": 91.01
  },
  {
    "date": "2009-01-08T00:00:00.000Z",
    "value": 92.7
  },
  {
    "date": "2009-01-09T00:00:00.000Z",
    "value": 90.58
  },
  {
    "date": "2009-01-11T00:00:00.000Z",
    "value": 88.66
  },
  {
    "date": "2009-01-12T00:00:00.000Z",
    "value": 87.71
  },
  {
    "date": "2009-01-13T00:00:00.000Z",
    "value": 85.33
  },
  {
    "date": "2009-01-14T00:00:00.000Z",
    "value": 83.38
  },
  {
    "date": "2009-01-15T00:00:00.000Z",
    "value": 82.33
  },
  {
    "date": "2009-01-19T00:00:00.000Z",
    "value": 78.2
  },
  {
    "date": "2009-01-20T00:00:00.000Z",
    "value": 82.83
  },
  {
    "date": "2009-01-21T00:00:00.000Z",
    "value": 88.36
  },
  {
    "date": "2009-01-22T00:00:00.000Z",
    "value": 88.36
  },
  {
    "date": "2009-01-25T00:00:00.000Z",
    "value": 89.64
  },
  {
    "date": "2009-01-26T00:00:00.000Z",
    "value": 90.73
  },
  {
    "date": "2009-01-27T00:00:00.000Z",
    "value": 94.2
  },
  {
    "date": "2009-01-28T00:00:00.000Z",
    "value": 93
  },
  {
    "date": "2009-01-29T00:00:00.000Z",
    "value": 90.13
  },
  {
    "date": "2009-02-02T00:00:00.000Z",
    "value": 91.51
  },
  {
    "date": "2009-02-03T00:00:00.000Z",
    "value": 92.98
  },
  {
    "date": "2009-02-04T00:00:00.000Z",
    "value": 93.55
  },
  {
    "date": "2009-02-05T00:00:00.000Z",
    "value": 96.46
  },
  {
    "date": "2009-02-06T00:00:00.000Z",
    "value": 99.72
  },
  {
    "date": "2009-02-09T00:00:00.000Z",
    "value": 102.51
  },
  {
    "date": "2009-02-09T00:00:00.000Z",
    "value": 97.83
  },
  {
    "date": "2009-02-10T00:00:00.000Z",
    "value": 96.82
  },
  {
    "date": "2009-02-11T00:00:00.000Z",
    "value": 99.27
  },
  {
    "date": "2009-02-12T00:00:00.000Z",
    "value": 99.16
  },
  {
    "date": "2009-02-16T00:00:00.000Z",
    "value": 94.53
  },
  {
    "date": "2009-02-17T00:00:00.000Z",
    "value": 94.37
  },
  {
    "date": "2009-02-18T00:00:00.000Z",
    "value": 90.64
  },
  {
    "date": "2009-02-19T00:00:00.000Z",
    "value": 91.2
  },
  {
    "date": "2009-02-22T00:00:00.000Z",
    "value": 86.95
  },
  {
    "date": "2009-02-23T00:00:00.000Z",
    "value": 90.25
  },
  {
    "date": "2009-02-24T00:00:00.000Z",
    "value": 91.16
  },
  {
    "date": "2009-02-25T00:00:00.000Z",
    "value": 89.19
  },
  {
    "date": "2009-02-26T00:00:00.000Z",
    "value": 89.31
  },
  {
    "date": "2009-03-02T00:00:00.000Z",
    "value": 87.94
  },
  {
    "date": "2009-03-03T00:00:00.000Z",
    "value": 88.37
  },
  {
    "date": "2009-03-04T00:00:00.000Z",
    "value": 91.17
  },
  {
    "date": "2009-03-05T00:00:00.000Z",
    "value": 88.84
  },
  {
    "date": "2009-03-06T00:00:00.000Z",
    "value": 85.3
  },
  {
    "date": "2009-03-09T00:00:00.000Z",
    "value": 83.11
  },
  {
    "date": "2009-03-09T00:00:00.000Z",
    "value": 88.63
  },
  {
    "date": "2009-03-10T00:00:00.000Z",
    "value": 92.68
  },
  {
    "date": "2009-03-11T00:00:00.000Z",
    "value": 96.35
  },
  {
    "date": "2009-03-12T00:00:00.000Z",
    "value": 95.93
  },
  {
    "date": "2009-03-15T00:00:00.000Z",
    "value": 95.42
  },
  {
    "date": "2009-03-16T00:00:00.000Z",
    "value": 99.66
  },
  {
    "date": "2009-03-17T00:00:00.000Z",
    "value": 101.52
  },
  {
    "date": "2009-03-18T00:00:00.000Z",
    "value": 101.62
  },
  {
    "date": "2009-03-19T00:00:00.000Z",
    "value": 101.59
  },
  {
    "date": "2009-03-22T00:00:00.000Z",
    "value": 107.66
  },
  {
    "date": "2009-03-23T00:00:00.000Z",
    "value": 106.5
  },
  {
    "date": "2009-03-24T00:00:00.000Z",
    "value": 106.49
  },
  {
    "date": "2009-03-25T00:00:00.000Z",
    "value": 109.87
  },
  {
    "date": "2009-03-26T00:00:00.000Z",
    "value": 106.85
  },
  {
    "date": "2009-03-29T00:00:00.000Z",
    "value": 104.49
  },
  {
    "date": "2009-03-30T00:00:00.000Z",
    "value": 105.12
  },
  {
    "date": "2009-04-01T00:00:00.000Z",
    "value": 108.69
  },
  {
    "date": "2009-04-02T00:00:00.000Z",
    "value": 112.71
  },
  {
    "date": "2009-04-03T00:00:00.000Z",
    "value": 115.99
  },
  {
    "date": "2009-04-06T00:00:00.000Z",
    "value": 118.45
  },
  {
    "date": "2009-04-07T00:00:00.000Z",
    "value": 115
  },
  {
    "date": "2009-04-08T00:00:00.000Z",
    "value": 116.32
  }
]
